user_sdk/__init__.py
user_sdk/domain.py
user_sdk/error.py
user_sdk/log.py
user_sdk/openid_connect.py
user_sdk/test_openid_connect.py
user_sdk/test_user.py
user_sdk/user_service.py
user_sdk-0.0.61.dist-info/METADATA
user_sdk-0.0.61.dist-info/WHEEL
user_sdk-0.0.61.dist-info/top_level.txt
user_sdk-0.0.61.dist-info/RECORD
