Metadata-Version: 2.1
Name: user-sdk
Version: 0.0.61
Summary: Interface for user auth/profile backend
Home-page: https://github.com/shuttl-tech/user_sdk
Author: Shuttl
Author-email: paul.kuruvilla@shuttl.com
License: MIT
Platform: UNKNOWN
Classifier: Programming Language :: Python :: 3.7
Classifier: License :: OSI Approved :: MIT License
Classifier: Operating System :: OS Independent
Requires-Dist: requests
Requires-Dist: pyshuttlis
Requires-Dist: shuttl-geo
Requires-Dist: python-jose
Requires-Dist: cachetools
Provides-Extra: test
Requires-Dist: pytest ; extra == 'test'
Requires-Dist: pytest-runner ; extra == 'test'
Requires-Dist: pytest-cov ; extra == 'test'
Requires-Dist: pytest-pep8 ; extra == 'test'
Requires-Dist: responses ; extra == 'test'
